FreeSimpleGUI/__init__.py
FreeSimpleGUI/_utils.py
FreeSimpleGUI/themes.py
FreeSimpleGUI/tray.py
FreeSimpleGUI/window.py
FreeSimpleGUI/elements/__init__.py
FreeSimpleGUI/elements/base.py
FreeSimpleGUI/elements/button.py
FreeSimpleGUI/elements/calendar.py
FreeSimpleGUI/elements/canvas.py
FreeSimpleGUI/elements/checkbox.py
FreeSimpleGUI/elements/column.py
FreeSimpleGUI/elements/combo.py
FreeSimpleGUI/elements/error.py
FreeSimpleGUI/elements/frame.py
FreeSimpleGUI/elements/graph.py
FreeSimpleGUI/elements/helpers.py
FreeSimpleGUI/elements/image.py
FreeSimpleGUI/elements/input.py
FreeSimpleGUI/elements/list_box.py
FreeSimpleGUI/elements/menu.py
FreeSimpleGUI/elements/multiline.py
FreeSimpleGUI/elements/option_menu.py
FreeSimpleGUI/elements/pane.py
FreeSimpleGUI/elements/progress_bar.py
FreeSimpleGUI/elements/radio.py
FreeSimpleGUI/elements/separator.py
FreeSimpleGUI/elements/sizegrip.py
FreeSimpleGUI/elements/slider.py
FreeSimpleGUI/elements/spin.py
FreeSimpleGUI/elements/status_bar.py
FreeSimpleGUI/elements/stretch.py
FreeSimpleGUI/elements/tab.py
FreeSimpleGUI/elements/table.py
FreeSimpleGUI/elements/text.py
FreeSimpleGUI/elements/tree.py
freesimplegui-5.2.0.dist-info/METADATA
freesimplegui-5.2.0.dist-info/NOTICE
freesimplegui-5.2.0.dist-info/WHEEL
freesimplegui-5.2.0.dist-info/entry_points.txt
freesimplegui-5.2.0.dist-info/top_level.txt
freesimplegui-5.2.0.dist-info/RECORD
