Metadata-Version: 2.2
Name: FreeSimpleGUI
Version: 5.2.0
Summary: The free-forever Python GUI framework.
Home-page: https://github.com/spyoungtech/FreeSimpleGui
Maintainer: Spencer Phillip Young
Maintainer-email: spencer.young@spyoung.com
Keywords: PySimpleGui fork GUI UI tkinter Qt WxPython Remi wrapper simple easy beginner novice student graphics progressbar progressmeter
Classifier: Programming Language :: Python :: 3
Classifier: Programming Language :: Python :: 3.7
Classifier: Programming Language :: Python :: 3.8
Classifier: Programming Language :: Python :: 3.9
Classifier: Programming Language :: Python :: 3.10
Classifier: Programming Language :: Python :: 3.11
Classifier: Programming Language :: Python :: 3.12
Classifier: License :: OSI Approved :: GNU Lesser General Public License v3 or later (LGPLv3+)
Classifier: Topic :: Multimedia :: Graphics
Classifier: Operating System :: OS Independent
License-File: NOTICE
